Workbook

Sheet Sales Data
A1: ID | B1: Category | C1: Cost | D1: Price | E1: Sold | F1: Status | G1: Margin
A2: 1 | B2: T-Shirt | C2: 200 | D2: 360 | E2: =TRUE() -> TRUE | F2: Sold | G2: =D2-C2 -> 160
A3: 2 | B3: T-Shirt | C3: 100 | D3: 390 | E3: =TRUE() -> TRUE | F3: Sold | G3: =D3-C3 -> 290
A4: 3 | B4: T-Shirt | C4: 130 | D4: 380 | E4: =TRUE() -> TRUE | F4: Sold | G4: =D4-C4 -> 250
A5: 4 | B5: T-Shirt | C5: 120 | D5: 360 | E5: =FALSE() -> FALSE | F5: Unsold | G5: =D5-C5 -> 240
A6: 5 | B6: T-Shirt | C6: 200 | D6: 430 | E6: =TRUE() -> TRUE | F6: Sold | G6: =D6-C6 -> 230
A7: 6 | B7: T-Shirt | C7: 110 | D7: 440 | E7: =FALSE() -> FALSE | F7: Unsold | G7: =D7-C7 -> 330
A8: 7 | B8: T-Shirt | C8: 160 | D8: 350 | E8: =TRUE() -> TRUE | F8: Sold | G8: =D8-C8 -> 190
A9: 8 | B9: T-Shirt | C9: 100 | D9: 360 | E9: =TRUE() -> TRUE | F9: Sold | G9: =D9-C9 -> 260
A10: 9 | B10: T-Shirt | C10: 130 | D10: 380 | E10: =FALSE() -> FALSE | F10: Unsold | G10: =D10-C10 -> 250
A11: 10 | B11: T-Shirt | C11: 180 | D11: 440 | E11: =TRUE() -> TRUE | F11: Sold | G11: =D11-C11 -> 260
A12: 11 | B12: T-Shirt | C12: 100 | D12: 430 | E12: =FALSE() -> FALSE | F12: Unsold | G12: =D12-C12 -> 330
A13: 12 | B13: T-Shirt | C13: 130 | D13: 450 | E13: =TRUE() -> TRUE | F13: Sold | G13: =D13-C13 -> 320
A14: 13 | B14: T-Shirt | C14: 180 | D14: 410 | E14: =TRUE() -> TRUE | F14: Sold | G14: =D14-C14 -> 230
A15: 14 | B15: T-Shirt | C15: 130 | D15: 420 | E15: =FALSE() -> FALSE | F15: Unsold | G15: =D15-C15 -> 290
A16: 15 | B16: T-Shirt | C16: 190 | D16: 390 | E16: =TRUE() -> TRUE | F16: Sold | G16: =D16-C16 -> 200
A17: 16 | B17: T-Shirt | C17: 100 | D17: 370 | E17: =TRUE() -> TRUE | F17: Sold | G17: =D17-C17 -> 270
A18: 17 | B18: T-Shirt | C18: 160 | D18: 400 | E18: =TRUE() -> TRUE | F18: Sold | G18: =D18-C18 -> 240
A19: 18 | B19: T-Shirt | C19: 140 | D19: 370 | E19: =TRUE() -> TRUE | F19: Sold | G19: =D19-C19 -> 230
A20: 19 | B20: T-Shirt | C20: 130 | D20: 400 | E20: =TRUE() -> TRUE | F20: Sold | G20: =D20-C20 -> 270
A21: 20 | B21: T-Shirt | C21: 110 | D21: 360 | E21: =TRUE() -> TRUE | F21: Sold | G21: =D21-C21 -> 250
A22: 21 | B22: T-Shirt | C22: 160 | D22: 360 | E22: =TRUE() -> TRUE | F22: Sold | G22: =D22-C22 -> 200
A23: 22 | B23: T-Shirt | C23: 150 | D23: 400 | E23: =TRUE() -> TRUE | F23: Sold | G23: =D23-C23 -> 250
A24: 23 | B24: T-Shirt | C24: 190 | D24: 390 | E24: =TRUE() -> TRUE | F24: Sold | G24: =D24-C24 -> 200
A25: 24 | B25: T-Shirt | C25: 100 | D25: 420 | E25: =TRUE() -> TRUE | F25: Sold | G25: =D25-C25 -> 320
A26: 25 | B26: T-Shirt | C26: 180 | D26: 360 | E26: =TRUE() -> TRUE | F26: Sold | G26: =D26-C26 -> 180
A27: 26 | B27: T-Shirt | C27: 160 | D27: 360 | E27: =TRUE() -> TRUE | F27: Sold | G27: =D27-C27 -> 200
... A30: 29 | B30: T-Shirt | C30: 150 | D30: 440 | E30: =TRUE() -> TRUE | F30: Sold | G30: =D30-C30 -> 290
A31: 30 | B31: T-Shirt | C31: 130 | D31: 360 | E31: =FALSE() -> FALSE | F31: Unsold | G31: =D31-C31 -> 230
A32: 31 | B32: T-Shirt | C32: 100 | D32: 450 | E32: =TRUE() -> TRUE | F32: Sold | G32: =D32-C32 -> 350
A33: 32 | B33: T-Shirt | C33: 130 | D33: 390 | E33: =TRUE() -> TRUE | F33: Sold | G33: =D33-C33 -> 260
A34: 33 | B34: T-Shirt | C34: 110 | D34: 380 | E34: =TRUE() -> TRUE | F34: Sold | G34: =D34-C34 -> 270
A35: 34 | B35: T-Shirt | C35: 110 | D35: 410 | E35: =FALSE() -> FALSE | F35: Unsold | G35: =D35-C35 -> 300
A36: 35 | B36: T-Shirt | C36: 140 | D36: 420 | E36: =TRUE() -> TRUE | F36: Sold | G36: =D36-C36 -> 280
A37: 36 | B37: T-Shirt | C37: 200 | D37: 400 | E37: =TRUE() -> TRUE | F37: Sold | G37: =D37-C37 -> 200
A38: 37 | B38: T-Shirt | C38: 120 | D38: 400 | E38: =TRUE() -> TRUE | F38: Sold | G38: =D38-C38 -> 280
A39: 38 | B39: T-Shirt | C39: 150 | D39: 380 | E39: =TRUE() -> TRUE | F39: Sold | G39: =D39-C39 -> 230
A40: 39 | B40: T-Shirt | C40: 200 | D40: 390 | E40: =TRUE() -> TRUE | F40: Sold | G40: =D40-C40 -> 190
A41: 40 | B41: T-Shirt | C41: 200 | D41: 450 | E41: =TRUE() -> TRUE | F41: Sold | G41: =D41-C41 -> 250
A42: 41 | B42: T-Shirt | C42: 110 | D42: 440 | E42: =FALSE() -> FALSE | F42: Unsold | G42: =D42-C42 -> 330
A43: 42 | B43: T-Shirt | C43: 200 | D43: 370 | E43: =FALSE() -> FALSE | F43: Unsold | G43: =D43-C43 -> 170
A44: 43 | B44: T-Shirt | C44: 180 | D44: 380 | E44: =FALSE() -> FALSE | F44: Unsold | G44: =D44-C44 -> 200
A45: 44 | B45: T-Shirt | C45: 120 | D45: 420 | E45: =TRUE() -> TRUE | F45: Sold | G45: =D45-C45 -> 300
A46: 45 | B46: T-Shirt | C46: 160 | D46: 390 | E46: =TRUE() -> TRUE | F46: Sold | G46: =D46-C46 -> 230
A47: 46 | B47: T-Shirt | C47: 200 | D47: 430 | E47: =FALSE() -> FALSE | F47: Unsold | G47: =D47-C47 -> 230
A48: 47 | B48: T-Shirt | C48: 130 | D48: 450 | E48: =TRUE() -> TRUE | F48: Sold | G48: =D48-C48 -> 320
A49: 48 | B49: T-Shirt | C49: 150 | D49: 350 | E49: =TRUE() -> TRUE | F49: Sold | G49: =D49-C49 -> 200
A50: 49 | B50: T-Shirt | C50: 130 | D50: 350 | E50: =TRUE() -> TRUE | F50: Sold | G50: =D50-C50 -> 220
A51: 50 | B51: T-Shirt | C51: 150 | D51: 410 | E51: =TRUE() -> TRUE | F51: Sold | G51: =D51-C51 -> 260
A52: 51 | B52: T-Shirt | C52: 140 | D52: 360 | E52: =TRUE() -> TRUE | F52: Sold | G52: =D52-C52 -> 220
A53: 52 | B53: T-Shirt | C53: 130 | D53: 440 | E53: =TRUE() -> TRUE | F53: Sold | G53: =D53-C53 -> 310
A54: 53 | B54: T-Shirt | C54: 150 | D54: 380 | E54: =TRUE() -> TRUE | F54: Sold | G54: =D54-C54 -> 230
A55: 54 | B55: T-Shirt | C55: 200 | D55: 420 | E55: =TRUE() -> TRUE | F55: Sold | G55: =D55-C55 -> 220
A56: 55 | B56: T-Shirt | C56: 160 | D56: 450 | E56: =TRUE() -> TRUE | F56: Sold | G56: =D56-C56 -> 290
A57: 56 | B57: T-Shirt | C57: 170 | D57: 370 | E57: =TRUE() -> TRUE | F57: Sold | G57: =D57-C57 -> 200
A58: 57 | B58: T-Shirt | C58: 140 | D58: 370 | E58: =TRUE() -> TRUE | F58: Sold | G58: =D58-C58 -> 230
A59: 58 | B59: T-Shirt | C59: 130 | D59: 430 | E59: =TRUE() -> TRUE | F59: Sold | G59: =D59-C59 -> 300
A60: 59 | B60: T-Shirt | C60: 180 | D60: 390 | E60: =FALSE() -> FALSE | F60: Unsold | G60: =D60-C60 -> 210
A61: 60 | B61: T-Shirt | C61: 190 | D61: 410 | E61: =TRUE() -> TRUE | F61: Sold | G61: =D61-C61 -> 220
A62: 61 | B62: Shirt | C62: 270 | D62: 560 | E62: =TRUE() -> TRUE | F62: Sold | G62: =D62-C62 -> 290
A63: 62 | B63: Shirt | C63: 220 | D63: 490 | E63: =TRUE() -> TRUE | F63: Sold | G63: =D63-C63 -> 270
A64: 63 | B64: Shirt | C64: 300 | D64: 470 | E64: =TRUE() -> TRUE | F64: Sold | G64: =D64-C64 -> 170
A65: 64 | B65: Shirt | C65: 160 | D65: 480 | E65: =TRUE() -> TRUE | F65: Sold | G65: =D65-C65 -> 320
A66: 65 | B66: Shirt | C66: 190 | D66: 650 | E66: =TRUE() -> TRUE | F66: Sold | G66: =D66-C66 -> 460
A67: 66 | B67: Shirt | C67: 200 | D67: 700 | E67: =FALSE() -> FALSE | F67: Unsold | G67: =D67-C67 -> 500
A68: 67 | B68: Shirt | C68: 280 | D68: 640 | E68: =TRUE() -> TRUE | F68: Sold | G68: =D68-C68 -> 360
A69: 68 | B69: Shirt | C69: 170 | D69: 570 | E69: =TRUE() -> TRUE | F69: Sold | G69: =D69-C69 -> 400
A70: 69 | B70: Shirt | C70: 270 | D70: 640 | E70: =FALSE() -> FALSE | F70: Unsold | G70: =D70-C70 -> 370
A71: 70 | B71: Shirt | C71: 290 | D71: 610 | E71: =TRUE() -> TRUE | F71: Sold | G71: =D71-C71 -> 320
A72: 71 | B72: Shirt | C72: 230 | D72: 620 | E72: =FALSE() -> FALSE | F72: Unsold | G72: =D72-C72 -> 390
A73: 72 | B73: Shirt | C73: 150 | D73: 660 | E73: =FALSE() -> FALSE | F73: Unsold | G73: =D73-C73 -> 510
A74: 73 | B74: Shirt | C74: 180 | D74: 660 | E74: =TRUE() -> TRUE | F74: Sold | G74: =D74-C74 -> 480
A75: 74 | B75: Shirt | C75: 230 | D75: 690 | E75: =TRUE() -> TRUE | F75: Sold | G75: =D75-C75 -> 460
A76: 75 | B76: Shirt | C76: 250 | D76: 480 | E76: =TRUE() -> TRUE | F76: Sold | G76: =D76-C76 -> 230
A77: 76 | B77: Shirt | C77: 240 | D77: 580 | E77: =TRUE() -> TRUE | F77: Sold | G77: =D77-C77 -> 340
A78: 77 | B78: Shirt | C78: 200 | D78: 590 | E78: =TRUE() -> TRUE | F78: Sold | G78: =D78-C78 -> 390
A79: 78 | B79: Shirt | C79: 150 | D79: 680 | E79: =TRUE() -> TRUE | F79: Sold | G79: =D79-C79 -> 530
A80: 79 | B80: Shirt | C80: 230 | D80: 610 | E80: =TRUE() -> TRUE | F80: Sold | G80: =D80-C80 -> 380
A81: 80 | B81: Shirt | C81: 200 | D81: 610 | E81: =TRUE() -> TRUE | F81: Sold | G81: =D81-C81 -> 410
A82: 81 | B82: Shirt | C82: 180 | D82: 650 | E82: =TRUE() -> TRUE | F82: Sold | G82: =D82-C82 -> 470
A83: 82 | B83: Shirt | C83: 240 | D83: 650 | E83: =TRUE() -> TRUE | F83: Sold | G83: =D83-C83 -> 410
A84: 83 | B84: Shirt | C84: 210 | D84: 490 | E84: =TRUE() -> TRUE | F84: Sold | G84: =D84-C84 -> 280
A85: 84 | B85: Shirt | C85: 260 | D85: 690 | E85: =TRUE() -> TRUE | F85: Sold | G85: =D85-C85 -> 430
... A88: 87 | B88: Shirt | C88: 250 | D88: 600 | E88: =TRUE() -> TRUE | F88: Sold | G88: =D88-C88 -> 350
A89: 88 | B89: Shirt | C89: 150 | D89: 480 | E89: =FALSE() -> FALSE | F89: Unsold | G89: =D89-C89 -> 330
A90: 89 | B90: Shirt | C90: 260 | D90: 700 | E90: =FALSE() -> FALSE | F90: Unsold | G90: =D90-C90 -> 440
A91: 90 | B91: Shirt | C91: 240 | D91: 520 | E91: =TRUE() -> TRUE | F91: Sold | G91: =D91-C91 -> 280
A92: 91 | B92: Shirt | C92: 160 | D92: 520 | E92: =TRUE() -> TRUE | F92: Sold | G92: =D92-C92 -> 360
A93: 92 | B93: Shirt | C93: 170 | D93: 470 | E93: =TRUE() -> TRUE | F93: Sold | G93: =D93-C93 -> 300
A94: 93 | B94: Shirt | C94: 300 | D94: 470 | E94: =TRUE() -> TRUE | F94: Sold | G94: =D94-C94 -> 170
A95: 94 | B95: Shirt | C95: 190 | D95: 490 | E95: =TRUE() -> TRUE | F95: Sold | G95: =D95-C95 -> 300
A96: 95 | B96: Shirt | C96: 300 | D96: 620 | E96: =TRUE() -> TRUE | F96: Sold | G96: =D96-C96 -> 320
A97: 96 | B97: Shirt | C97: 200 | D97: 530 | E97: =TRUE() -> TRUE | F97: Sold | G97: =D97-C97 -> 330
A98: 97 | B98: Shirt | C98: 280 | D98: 510 | E98: =FALSE() -> FALSE | F98: Unsold | G98: =D98-C98 -> 230
A99: 98 | B99: Shirt | C99: 210 | D99: 670 | E99: =FALSE() -> FALSE | F99: Unsold | G99: =D99-C99 -> 460
A100: 99 | B100: Shirt | C100: 240 | D100: 570 | E100: =TRUE() -> TRUE | F100: Sold | G100: =D100-C100 -> 330
A101: 100 | B101: Shirt | C101: 260 | D101: 590 | E101: =TRUE() -> TRUE | F101: Sold | G101: =D101-C101 -> 330

Sheet Summary
A1: Drippy But Broke — Sprint Summary
A3: Metric | B3: Value
A4: Total pieces sourced | B4: =COUNTA('Sales Data'!A2:A101) -> 100
A5: Pieces sold | B5: =COUNTIF('Sales Data'!F2:F101,"Sold") -> 80
A6: Pieces unsold | B6: =COUNTIF('Sales Data'!F2:F101,"Unsold") -> 20
A7: Sell-through rate | B7: =B5/B4 -> 0.8
A8: Total sourcing cost | B8: =SUM('Sales Data'!C2:C101) -> 17840
A9: Total revenue (sold only) | B9: =SUMIF('Sales Data'!F2:F101,"Sold",'Sales Data'!D2:D101) -> 37570
A10: Net profit | B10: =B9-B8 -> 19730
A11: Return on cost | B11: =B10/B8 -> 1.1059417
A12: Average selling price (all stock) | B12: =AVERAGE('Sales Data'!D2:D101) -> 473.6
A13: Breakeven units (cost / avg price) | B13: =B8/B12 -> 37.668919
A14: Unsold stock value (at cost) | B14: =SUMIF('Sales Data'!F2:F101,"Unsold",'Sales Data'!C2:C101) -> 3450
A16: Formulas reference the Sales Data sheet directly — recalculates if you edit costs/prices/sold status there.

Sheet Category Breakdown
A1: Metric | B1: T-Shirt | C1: Shirt | D1: Total
A2: Units sourced | B2: =COUNTIF('Sales Data'!$B$2:$B$101,$B$1) -> 60 | C2: =COUNTIF('Sales Data'!$B$2:$B$101,$C$1) -> 40 | D2: =B2+C2 -> 100
A3: Units sold | B3: =COUNTIFS('Sales Data'!$B$2:$B$101,$B$1,'Sales Data'!$F$2:$F$101,"Sold") -> 48 | C3: =COUNTIFS('Sales Data'!$B$2:$B$101,$C$1,'Sales Data'!$F$2:$F$101,"Sold") -> 32 | D3: =B3+C3 -> 80
A4: Units unsold | B4: =COUNTIFS('Sales Data'!$B$2:$B$101,$B$1,'Sales Data'!$F$2:$F$101,"Unsold") -> 12 | C4: =COUNTIFS('Sales Data'!$B$2:$B$101,$C$1,'Sales Data'!$F$2:$F$101,"Unsold") -> 8 | D4: =B4+C4 -> 20
A5: Cost | B5: =SUMIF('Sales Data'!$B$2:$B$101,$B$1,'Sales Data'!$C$2:$C$101) -> 8980 | C5: =SUMIF('Sales Data'!$B$2:$B$101,$C$1,'Sales Data'!$C$2:$C$101) -> 8860 | D5: =B5+C5 -> 17840
A6: Revenue | B6: =SUMIFS('Sales Data'!$D$2:$D$101,'Sales Data'!$B$2:$B$101,$B$1,'Sales Data'!$F$2:$F$101,"Sold") -> 19080 | C6: =SUMIFS('Sales Data'!$D$2:$D$101,'Sales Data'!$B$2:$B$101,$C$1,'Sales Data'!$F$2:$F$101,"Sold") -> 18490 | D6: =B6+C6 -> 37570
A7: Profit | B7: =B6-B5 -> 10100 | C7: =C6-C5 -> 9630 | D7: =B7+C7 -> 19730
A8: Avg selling price | B8: =AVERAGEIF('Sales Data'!$B$2:$B$101,$B$1,'Sales Data'!$D$2:$D$101) -> 398.16667 | C8: =AVERAGEIF('Sales Data'!$B$2:$B$101,$C$1,'Sales Data'!$D$2:$D$101) -> 586.75 | D8: =Summary!B12 -> 473.6
A9: Breakeven units | B9: =B5/B8 -> 22.55337 | C9: =C5/C8 -> 15.100128 | D9: =Summary!B13 -> 37.668919
